{
  "id": "9a1aa2eb-728e-405e-8ec7-3a144971fea1",
  "title": "Meridian Tech Buys Data Startup Lightwave for $2.3 Billion",
  "source": "The Business Standard",
  "date": "2026-02-10",
  "body": "Palo Alto-based Meridian Technologies has agreed to purchase Lightwave Analytics for $2.3 billion, the companies said in a joint statement. The deal marks Meridian's largest acquisition since its $900 million purchase of CloudScale in 2023. Lightwave, which specializes in real-time data processing, will become part of Meridian's cloud services unit. Lightwave founder Priya Sharma will join Meridian as Senior Vice President of Analytics following the close of the transaction. Meridian shares rose 4% in early trading on the news."
}